device.cp36-win_amd64.pyd
WindowsDevices-1.0.dist-info/LICENSE
WindowsDevices-1.0.dist-info/METADATA
WindowsDevices-1.0.dist-info/WHEEL
WindowsDevices-1.0.dist-info/top_level.txt
WindowsDevices-1.0.dist-info/RECORD
