Metadata-Version: 2.1
Name: WindowsDevices
Version: 1.0
Summary: Get device list with DirectShow
Home-page: UNKNOWN
Author: UNKNOWN
Author-email: UNKNOWN
License: UNKNOWN
Platform: UNKNOWN
